keychainClient/KeychainClient.py
keychainClient/__init__.py
keychainClient/crypto/KeychainEncryptor.py
keychainClient/crypto/__init__.py
keychainClient/exception/KeychainEncryptionException.py
keychainClient/exception/KeychainNotExistException.py
keychainClient/exception/__init__.py
keychainClient/model/KeySpec.py
keychainClient/model/__init__.py
keychainClient/protobuf/__init__.py
keychainClient/protobuf/derived_key_pb2.py
keychainClient/protobuf/keychain_pb2.py
p1_harpocrates_sdk-0.3.1.dist-info/LICENSE
p1_harpocrates_sdk-0.3.1.dist-info/METADATA
p1_harpocrates_sdk-0.3.1.dist-info/WHEEL
p1_harpocrates_sdk-0.3.1.dist-info/top_level.txt
p1_harpocrates_sdk-0.3.1.dist-info/RECORD
